__init__.py
iugu/__init__.py
iugu/api.py
iugu/apis/__init__.py
iugu/apis/customers.py
iugu/apis/invoices.py
iugu/apis/plans.py
iugu/apis/subscriptions.py
iugu/apis/webhooks.py
iugu/dtos/__init__.py
iugu/dtos/customer.py
iugu/dtos/invoice.py
iugu/dtos/keyvalue.py
iugu/dtos/plan.py
iugu/dtos/split.py
iugu/dtos/subscription.py
iugu/dtos/webhook.py
iugu_python_sdk-1.3.1.dist-info/licenses/LICENSE
iugu_python_sdk-1.3.1.dist-info/METADATA
iugu_python_sdk-1.3.1.dist-info/WHEEL
iugu_python_sdk-1.3.1.dist-info/top_level.txt
iugu_python_sdk-1.3.1.dist-info/RECORD
